[{"datasetObjectId":"144","dataObject":{"s3Uri":"s3://mini-amazon-go-henanwan/shenzhen_v1/frame_1604557248.7920978.jpg"},"annotations":[{"workerId":"private.us-west-2.2e770e9fc0ca9d2c","annotationData":{"content":"{\"boundingBox\":{\"boundingBoxes\":[{\"height\":137,\"label\":\"cocacola\",\"left\":87,\"top\":135,\"width\":136},{\"height\":139,\"label\":\"cocacola\",\"left\":236,\"top\":140,\"width\":132},{\"height\":224,\"label\":\"noodles\",\"left\":342,\"top\":1,\"width\":221},{\"height\":214,\"label\":\"noodles\",\"left\":314,\"top\":222,\"width\":219}],\"inputImageProperties\":{\"height\":480,\"width\":640}}}"}}]},{"datasetObjectId":"53","dataObject":{"s3Uri":"s3://mini-amazon-go-henanwan/shenzhen_v1/frame_1604547906.777072.jpg"},"annotations":[{"workerId":"private.us-west-2.2e770e9fc0ca9d2c","annotationData":{"content":"{\"boundingBox\":{\"boundingBoxes\":[{\"height\":221,\"label\":\"noodles\",\"left\":100,\"top\":177,\"width\":217},{\"height\":210,\"label\":\"noodles\",\"left\":328,\"top\":200,\"width\":206},{\"height\":409,\"label\":\"hand\",\"left\":364,\"top\":4,\"width\":276}],\"inputImageProperties\":{\"height\":480,\"width\":640}}}"}}]},{"datasetObjectId":"117","dataObject":{"s3Uri":"s3://mini-amazon-go-henanwan/shenzhen_v1/frame_1604547972.56478.jpg"},"annotations":[{"workerId":"private.us-west-2.2e770e9fc0ca9d2c","annotationData":{"content":"{\"boundingBox\":{\"boundingBoxes\":[],\"inputImageProperties\":{\"height\":480,\"width\":640}}}"}}]},{"datasetObjectId":"95","dataObject":{"s3Uri":"s3://mini-amazon-go-henanwan/shenzhen_v1/frame_1604547949.957794.jpg"},"annotations":[{"workerId":"private.us-west-2.2e770e9fc0ca9d2c","annotationData":{"content":"{\"boundingBox\":{\"boundingBoxes\":[{\"height\":269,\"label\":\"hand\",\"left\":13,\"top\":1,\"width\":382},{\"height\":130,\"label\":\"cocacola\",\"left\":0,\"top\":258,\"width\":56}],\"inputImageProperties\":{\"height\":480,\"width\":640}}}"}}]},{"datasetObjectId":"123","dataObject":{"s3Uri":"s3://mini-amazon-go-henanwan/shenzhen_v1/frame_1604547978.726913.jpg"},"annotations":[{"workerId":"private.us-west-2.2e770e9fc0ca9d2c","annotationData":{"content":"{\"boundingBox\":{\"boundingBoxes\":[{\"height\":228,\"label\":\"noodles\",\"left\":170,\"top\":70,\"width\":225}],\"inputImageProperties\":{\"height\":480,\"width\":640}}}"}}]}]